[{"source": {"type": "file", "filename": "214_00-00-24.024_00-00-26.400_David_neutral_neutral.txt", "content_type": "text/plain", "md5sum": "377f7a8d60d6778887cb56b441138c3a"}, "results": {"predictions": [{"file": "214_00-00-24.024_00-00-26.400_David_neutral_neutral.txt", "file_type": "text", "models": {"language": {"metadata": null, "grouped_predictions": [{"id": "unknown", "predictions": [{"text": "Yeah,", "position": {"begin": 0, "end": 5}, "time": null, "confidence": null, "speaker_confidence": null, "emotions": [{"name": "Admiration", "score": 0.003949932754039764}, {"name": "Adoration", "score": 0.0008262790506705642}, {"name": "Aesthetic Appreciation", "score": 0.004039265681058168}, {"name": "Amusement", "score": 0.016593826934695244}, {"name": "Anger", "score": 0.00782735738903284}, {"name": "Annoyance", "score": 0.2301340401172638}, {"name": "Anxiety", "score": 0.0037678538355976343}, {"name": "Awe", "score": 0.0018458941485732794}, {"name": "Awkwardness", "score": 0.04396587610244751}, {"name": "Boredom", "score": 0.49953407049179077}, {"name": "Calmness", "score": 0.16343115270137787}, {"name": "Concentration", "score": 0.019610516726970673}, {"name": "Confusion", "score": 0.03589019551873207}, {"name": "Contemplation", "score": 0.046651728451251984}, {"name": "Contempt", "score": 0.10142754018306732}, {"name": "Contentment", "score": 0.058753617107868195}, {"name": "Craving", "score": 0.0007236345554701984}, {"name": "Desire", "score": 0.0003586717357393354}, {"name": "Determination", "score": 0.011728757992386818}, {"name": "Disappointment", "score": 0.07922518253326416}, {"name": "Disapproval", "score": 0.09164755046367645}, {"name": "Disgust", "score": 0.009782087057828903}, {"name": "Distress", "score": 0.004838095512241125}, {"name": "Doubt", "score": 0.049284305423498154}, {"name": "Ecstasy", "score": 0.00037662970134988427}, {"name": "Embarrassment", "score": 0.003989055287092924}, {"name": "Empathic Pain", "score": 0.004129420965909958}, {"name": "Enthusiasm", "score": 0.018441330641508102}, {"name": "Entrancement", "score": 0.0019638887606561184}, {"name": "Envy", "score": 0.0027700853534042835}, {"name": "Excitement", "score": 0.006166050676256418}, {"name": "Fear", "score": 0.0006911126547493041}, {"name": "Gratitude", "score": 0.00564079312607646}, {"name": "Guilt", "score": 0.0010413561249151826}, {"name": "Horror", "score": 0.00019596236234065145}, {"name": "Interest", "score": 0.03268894553184509}, {"name": "Joy", "score": 0.005159479565918446}, {"name": "Love", "score": 0.0005820575752295554}, {"name": "Nostalgia", "score": 0.0011006818385794759}, {"name": "Pain", "score": 0.0017556424718350172}, {"name": "Pride", "score": 0.004222802817821503}, {"name": "Realization", "score": 0.10680653899908066}, {"name": "Relief", "score": 0.019554005935788155}, {"name": "Romance", "score": 0.0002622432366479188}, {"name": "Sadness", "score": 0.0072287749499082565}, {"name": "Sarcasm", "score": 0.14965656399726868}, {"name": "Satisfaction", "score": 0.03888234868645668}, {"name": "Shame", "score": 0.004416265990585089}, {"name": "Surprise (negative)", "score": 0.03228124976158142}, {"name": "Surprise (positive)", "score": 0.01855684258043766}, {"name": "Sympathy", "score": 0.007696476299315691}, {"name": "Tiredness", "score": 0.07848571985960007}, {"name": "Triumph", "score": 0.009033695794641972}], "sentiment": null, "toxicity": null}, {"text": "I\u0092m", "position": {"begin": 6, "end": 9}, "time": null, "confidence": null, "speaker_confidence": null, "emotions": [{"name": "Admiration", "score": 0.002071053022518754}, {"name": "Adoration", "score": 0.0008716360898688436}, {"name": "Aesthetic Appreciation", "score": 0.002464852062985301}, {"name": "Amusement", "score": 0.01654122583568096}, {"name": "Anger", "score": 0.004660767037421465}, {"name": "Annoyance", "score": 0.07316254079341888}, {"name": "Anxiety", "score": 0.008998023346066475}, {"name": "Awe", "score": 0.001772246789187193}, {"name": "Awkwardness", "score": 0.008642509579658508}, {"name": "Boredom", "score": 0.053388070315122604}, {"name": "Calmness", "score": 0.35711708664894104}, {"name": "Concentration", "score": 0.02933427132666111}, {"name": "Confusion", "score": 0.006366295274347067}, {"name": "Contemplation", "score": 0.06650105863809586}, {"name": "Contempt", "score": 0.08147015422582626}, {"name": "Contentment", "score": 0.3357318341732025}, {"name": "Craving", "score": 0.0014894652413204312}, {"name": "Desire", "score": 0.00011299123434582725}, {"name": "Determination", "score": 0.09438145160675049}, {"name": "Disappointment", "score": 0.0073425727896392345}, {"name": "Disapproval", "score": 0.010700788348913193}, {"name": "Disgust", "score": 0.0030901271384209394}, {"name": "Distress", "score": 0.0072226617485284805}, {"name": "Doubt", "score": 0.013432247564196587}, {"name": "Ecstasy", "score": 0.0023505003191530704}, {"name": "Embarrassment", "score": 0.0011946153827011585}, {"name": "Empathic Pain", "score": 0.0024673165753483772}, {"name": "Enthusiasm", "score": 0.0477759912610054}, {"name": "Entrancement", "score": 0.002578740706667304}, {"name": "Envy", "score": 0.0006053007673472166}, {"name": "Excitement", "score": 0.014429408125579357}, {"name": "Fear", "score": 0.0013517985353246331}, {"name": "Gratitude", "score": 0.05030987784266472}, {"name": "Guilt", "score": 0.0016029931139200926}, {"name": "Horror", "score": 0.00011668195656966418}, {"name": "Interest", "score": 0.013554275035858154}, {"name": "Joy", "score": 0.02536507323384285}, {"name": "Love", "score": 0.0016359904548153281}, {"name": "Nostalgia", "score": 0.0002620340674184263}, {"name": "Pain", "score": 0.003051338717341423}, {"name": "Pride", "score": 0.044122885912656784}, {"name": "Realization", "score": 0.09565116465091705}, {"name": "Relief", "score": 0.10672753304243088}, {"name": "Romance", "score": 0.00016594001499470323}, {"name": "Sadness", "score": 0.004089121241122484}, {"name": "Sarcasm", "score": 0.2078135460615158}, {"name": "Satisfaction", "score": 0.24215711653232574}, {"name": "Shame", "score": 0.0020390753634274006}, {"name": "Surprise (negative)", "score": 0.0029536171350628138}, {"name": "Surprise (positive)", "score": 0.010178666561841965}, {"name": "Sympathy", "score": 0.0034479298628866673}, {"name": "Tiredness", "score": 0.11932843923568726}, {"name": "Triumph", "score": 0.06799977272748947}], "sentiment": null, "toxicity": null}, {"text": "just,", "position": {"begin": 10, "end": 15}, "time": null, "confidence": null, "speaker_confidence": null, "emotions": [{"name": "Admiration", "score": 0.0008335784077644348}, {"name": "Adoration", "score": 0.0004424213257152587}, {"name": "Aesthetic Appreciation", "score": 0.002140297321602702}, {"name": "Amusement", "score": 0.017030995339155197}, {"name": "Anger", "score": 0.006391832139343023}, {"name": "Annoyance", "score": 0.16330958902835846}, {"name": "Anxiety", "score": 0.03402600809931755}, {"name": "Awe", "score": 0.0008168047061190009}, {"name": "Awkwardness", "score": 0.10930593311786652}, {"name": "Boredom", "score": 0.20932483673095703}, {"name": "Calmness", "score": 0.22738896310329437}, {"name": "Concentration", "score": 0.014189977198839188}, {"name": "Confusion", "score": 0.07138178497552872}, {"name": "Contemplation", "score": 0.16191279888153076}, {"name": "Contempt", "score": 0.09427367150783539}, {"name": "Contentment", "score": 0.09616683423519135}, {"name": "Craving", "score": 0.0026567892637103796}, {"name": "Desire", "score": 0.00033125211484730244}, {"name": "Determination", "score": 0.013520914129912853}, {"name": "Disappointment", "score": 0.03660279139876366}, {"name": "Disapproval", "score": 0.0320294052362442}, {"name": "Disgust", "score": 0.005767555441707373}, {"name": "Distress", "score": 0.024189654737710953}, {"name": "Doubt", "score": 0.10724187642335892}, {"name": "Ecstasy", "score": 0.0005787783302366734}, {"name": "Embarrassment", "score": 0.012382573448121548}, {"name": "Empathic Pain", "score": 0.006887824274599552}, {"name": "Enthusiasm", "score": 0.007534906733781099}, {"name": "Entrancement", "score": 0.0030299231875687838}, {"name": "Envy", "score": 0.0014950091717764735}, {"name": "Excitement", "score": 0.0018872839864343405}, {"name": "Fear", "score": 0.0032780386973172426}, {"name": "Gratitude", "score": 0.031691309064626694}, {"name": "Guilt", "score": 0.01131054200232029}, {"name": "Horror", "score": 0.00021482599549926817}, {"name": "Interest", "score": 0.012858059257268906}, {"name": "Joy", "score": 0.004822821822017431}, {"name": "Love", "score": 0.0008153946837410331}, {"name": "Nostalgia", "score": 0.0008133055525831878}, {"name": "Pain", "score": 0.00830618292093277}, {"name": "Pride", "score": 0.005045105237513781}, {"name": "Realization", "score": 0.0681212767958641}, {"name": "Relief", "score": 0.03230525180697441}, {"name": "Romance", "score": 0.00042344772373326123}, {"name": "Sadness", "score": 0.025343606248497963}, {"name": "Sarcasm", "score": 0.2963573634624481}, {"name": "Satisfaction", "score": 0.03294987604022026}, {"name": "Shame", "score": 0.014968396164476871}, {"name": "Surprise (negative)", "score": 0.00525075476616621}, {"name": "Surprise (positive)", "score": 0.0027958324644714594}, {"name": "Sympathy", "score": 0.00801081582903862}, {"name": "Tiredness", "score": 0.33362528681755066}, {"name": "Triumph", "score": 0.004475761670619249}], "sentiment": null, "toxicity": null}, {"text": "I\u0092m", "position": {"begin": 16, "end": 19}, "time": null, "confidence": null, "speaker_confidence": null, "emotions": [{"name": "Admiration", "score": 0.0007210491457954049}, {"name": "Adoration", "score": 0.0004181876720394939}, {"name": "Aesthetic Appreciation", "score": 0.002297908067703247}, {"name": "Amusement", "score": 0.018763331696391106}, {"name": "Anger", "score": 0.0021777302026748657}, {"name": "Annoyance", "score": 0.06287437677383423}, {"name": "Anxiety", "score": 0.036197479814291}, {"name": "Awe", "score": 0.001004248159006238}, {"name": "Awkwardness", "score": 0.05179692432284355}, {"name": "Boredom", "score": 0.22041445970535278}, {"name": "Calmness", "score": 0.22569887340068817}, {"name": "Concentration", "score": 0.011898779310286045}, {"name": "Confusion", "score": 0.038711030036211014}, {"name": "Contemplation", "score": 0.07887598872184753}, {"name": "Contempt", "score": 0.035409729927778244}, {"name": "Contentment", "score": 0.13523198664188385}, {"name": "Craving", "score": 0.0028166836127638817}, {"name": "Desire", "score": 0.00032409190316684544}, {"name": "Determination", "score": 0.013659369200468063}, {"name": "Disappointment", "score": 0.02373393066227436}, {"name": "Disapproval", "score": 0.007775380741804838}, {"name": "Disgust", "score": 0.0022614197805523872}, {"name": "Distress", "score": 0.027834875509142876}, {"name": "Doubt", "score": 0.03737539052963257}, {"name": "Ecstasy", "score": 0.002233846578747034}, {"name": "Embarrassment", "score": 0.006274635437875986}, {"name": "Empathic Pain", "score": 0.005031751003116369}, {"name": "Enthusiasm", "score": 0.014148671180009842}, {"name": "Entrancement", "score": 0.0032792449928820133}, {"name": "Envy", "score": 0.0006119128665886819}, {"name": "Excitement", "score": 0.005262167192995548}, {"name": "Fear", "score": 0.002813044236972928}, {"name": "Gratitude", "score": 0.0225894283503294}, {"name": "Guilt", "score": 0.00482155429199338}, {"name": "Horror", "score": 0.0001775664131855592}, {"name": "Interest", "score": 0.007031099405139685}, {"name": "Joy", "score": 0.012201357632875443}, {"name": "Love", "score": 0.0007738604326732457}, {"name": "Nostalgia", "score": 0.00042630580719560385}, {"name": "Pain", "score": 0.01175080705434084}, {"name": "Pride", "score": 0.004138019867241383}, {"name": "Realization", "score": 0.09089239686727524}, {"name": "Relief", "score": 0.07625992596149445}, {"name": "Romance", "score": 0.0003760244871955365}, {"name": "Sadness", "score": 0.022584745660424232}, {"name": "Sarcasm", "score": 0.10448628664016724}, {"name": "Satisfaction", "score": 0.05513312295079231}, {"name": "Shame", "score": 0.007619260344654322}, {"name": "Surprise (negative)", "score": 0.0049003190360963345}, {"name": "Surprise (positive)", "score": 0.005501432344317436}, {"name": "Sympathy", "score": 0.0042998152785003185}, {"name": "Tiredness", "score": 0.4675627052783966}, {"name": "Triumph", "score": 0.008991903625428677}], "sentiment": null, "toxicity": null}, {"text": "just", "position": {"begin": 20, "end": 24}, "time": null, "confidence": null, "speaker_confidence": null, "emotions": [{"name": "Admiration", "score": 0.00039885909063741565}, {"name": "Adoration", "score": 0.000295561330858618}, {"name": "Aesthetic Appreciation", "score": 0.0010788908693939447}, {"name": "Amusement", "score": 0.017034590244293213}, {"name": "Anger", "score": 0.013583667576313019}, {"name": "Annoyance", "score": 0.20547671616077423}, {"name": "Anxiety", "score": 0.06660711765289307}, {"name": "Awe", "score": 0.0006848821067251265}, {"name": "Awkwardness", "score": 0.08376610279083252}, {"name": "Boredom", "score": 0.16226978600025177}, {"name": "Calmness", "score": 0.07682875543832779}, {"name": "Concentration", "score": 0.008062129840254784}, {"name": "Confusion", "score": 0.08585786819458008}, {"name": "Contemplation", "score": 0.05146098881959915}, {"name": "Contempt", "score": 0.04920339584350586}, {"name": "Contentment", "score": 0.037180278450250626}, {"name": "Craving", "score": 0.0035203953739255667}, {"name": "Desire", "score": 0.00046151786227710545}, {"name": "Determination", "score": 0.012169593013823032}, {"name": "Disappointment", "score": 0.04001330956816673}, {"name": "Disapproval", "score": 0.017021281644701958}, {"name": "Disgust", "score": 0.005791828967630863}, {"name": "Distress", "score": 0.08011838048696518}, {"name": "Doubt", "score": 0.043773103505373}, {"name": "Ecstasy", "score": 0.0016983958194032311}, {"name": "Embarrassment", "score": 0.012950179167091846}, {"name": "Empathic Pain", "score": 0.007422090508043766}, {"name": "Enthusiasm", "score": 0.007763128262013197}, {"name": "Entrancement", "score": 0.00225090398453176}, {"name": "Envy", "score": 0.0009493902907706797}, {"name": "Excitement", "score": 0.00329009466804564}, {"name": "Fear", "score": 0.004332313314080238}, {"name": "Gratitude", "score": 0.009189698845148087}, {"name": "Guilt", "score": 0.010796530172228813}, {"name": "Horror", "score": 0.0004291590885259211}, {"name": "Interest", "score": 0.0038288587238639593}, {"name": "Joy", "score": 0.006142075173556805}, {"name": "Love", "score": 0.0006250690203160048}, {"name": "Nostalgia", "score": 0.0004067094996571541}, {"name": "Pain", "score": 0.02936415560543537}, {"name": "Pride", "score": 0.002930962946265936}, {"name": "Realization", "score": 0.06860951334238052}, {"name": "Relief", "score": 0.035315580666065216}, {"name": "Romance", "score": 0.00039018059032969177}, {"name": "Sadness", "score": 0.038195736706256866}, {"name": "Sarcasm", "score": 0.12931160628795624}, {"name": "Satisfaction", "score": 0.018014268949627876}, {"name": "Shame", "score": 0.016531633213162422}, {"name": "Surprise (negative)", "score": 0.008681921288371086}, {"name": "Surprise (positive)", "score": 0.0031329342164099216}, {"name": "Sympathy", "score": 0.0053858389146625996}, {"name": "Tiredness", "score": 0.5341833829879761}, {"name": "Triumph", "score": 0.005372590851038694}], "sentiment": null, "toxicity": null}, {"text": "in", "position": {"begin": 25, "end": 27}, "time": null, "confidence": null, "speaker_confidence": null, "emotions": [{"name": "Admiration", "score": 0.0009519873419776559}, {"name": "Adoration", "score": 0.0006307153962552547}, {"name": "Aesthetic Appreciation", "score": 0.0036963578313589096}, {"name": "Amusement", "score": 0.008657737635076046}, {"name": "Anger", "score": 0.0041917115449905396}, {"name": "Annoyance", "score": 0.041644349694252014}, {"name": "Anxiety", "score": 0.1241622269153595}, {"name": "Awe", "score": 0.001432958641089499}, {"name": "Awkwardness", "score": 0.05541960522532463}, {"name": "Boredom", "score": 0.07434701919555664}, {"name": "Calmness", "score": 0.18146681785583496}, {"name": "Concentration", "score": 0.029156671836972237}, {"name": "Confusion", "score": 0.025418782606720924}, {"name": "Contemplation", "score": 0.039456989616155624}, {"name": "Contempt", "score": 0.023817140609025955}, {"name": "Contentment", "score": 0.1384696215391159}, {"name": "Craving", "score": 0.006706222891807556}, {"name": "Desire", "score": 0.001875067944638431}, {"name": "Determination", "score": 0.06344201415777206}, {"name": "Disappointment", "score": 0.010626361705362797}, {"name": "Disapproval", "score": 0.005737158469855785}, {"name": "Disgust", "score": 0.0027481517754495144}, {"name": "Distress", "score": 0.055326297879219055}, {"name": "Doubt", "score": 0.023129815235733986}, {"name": "Ecstasy", "score": 0.011338658630847931}, {"name": "Embarrassment", "score": 0.005004569888114929}, {"name": "Empathic Pain", "score": 0.003151754615828395}, {"name": "Enthusiasm", "score": 0.06838461011648178}, {"name": "Entrancement", "score": 0.005141891539096832}, {"name": "Envy", "score": 0.00045637463335879147}, {"name": "Excitement", "score": 0.045223042368888855}, {"name": "Fear", "score": 0.013086335733532906}, {"name": "Gratitude", "score": 0.030753223225474358}, {"name": "Guilt", "score": 0.0035993591882288456}, {"name": "Horror", "score": 0.0005763088702224195}, {"name": "Interest", "score": 0.015031012706458569}, {"name": "Joy", "score": 0.019903309643268585}, {"name": "Love", "score": 0.0006678728386759758}, {"name": "Nostalgia", "score": 0.00020831110305152833}, {"name": "Pain", "score": 0.008668544702231884}, {"name": "Pride", "score": 0.006238650064915419}, {"name": "Realization", "score": 0.05241982638835907}, {"name": "Relief", "score": 0.15074557065963745}, {"name": "Romance", "score": 0.0005391191807575524}, {"name": "Sadness", "score": 0.006539861671626568}, {"name": "Sarcasm", "score": 0.012743959203362465}, {"name": "Satisfaction", "score": 0.11307420581579208}, {"name": "Shame", "score": 0.005329025909304619}, {"name": "Surprise (negative)", "score": 0.005209476221352816}, {"name": "Surprise (positive)", "score": 0.011131426319479942}, {"name": "Sympathy", "score": 0.001825767452828586}, {"name": "Tiredness", "score": 0.32330188155174255}, {"name": "Triumph", "score": 0.03119383007287979}], "sentiment": null, "toxicity": null}, {"text": "town", "position": {"begin": 28, "end": 32}, "time": null, "confidence": null, "speaker_confidence": null, "emotions": [{"name": "Admiration", "score": 0.0006300382083281875}, {"name": "Adoration", "score": 0.000467824429506436}, {"name": "Aesthetic Appreciation", "score": 0.0031296624802052975}, {"name": "Amusement", "score": 0.009086189791560173}, {"name": "Anger", "score": 0.0037848346401005983}, {"name": "Annoyance", "score": 0.14253351092338562}, {"name": "Anxiety", "score": 0.02138758823275566}, {"name": "Awe", "score": 0.0004964133258908987}, {"name": "Awkwardness", "score": 0.05389240011572838}, {"name": "Boredom", "score": 0.3955235779285431}, {"name": "Calmness", "score": 0.43592318892478943}, {"name": "Concentration", "score": 0.024898838251829147}, {"name": "Confusion", "score": 0.01768174022436142}, {"name": "Contemplation", "score": 0.0483875572681427}, {"name": "Contempt", "score": 0.04039899632334709}, {"name": "Contentment", "score": 0.18205229938030243}, {"name": "Craving", "score": 0.003279170487076044}, {"name": "Desire", "score": 0.00030330262961797416}, {"name": "Determination", "score": 0.0192039106041193}, {"name": "Disappointment", "score": 0.030965186655521393}, {"name": "Disapproval", "score": 0.014727652072906494}, {"name": "Disgust", "score": 0.002941432176157832}, {"name": "Distress", "score": 0.01573675312101841}, {"name": "Doubt", "score": 0.014768761582672596}, {"name": "Ecstasy", "score": 0.0008964681765064597}, {"name": "Embarrassment", "score": 0.006425785832107067}, {"name": "Empathic Pain", "score": 0.0031005023047327995}, {"name": "Enthusiasm", "score": 0.01752016693353653}, {"name": "Entrancement", "score": 0.0019949553534388542}, {"name": "Envy", "score": 0.0005083936266601086}, {"name": "Excitement", "score": 0.005839322693645954}, {"name": "Fear", "score": 0.0013291644863784313}, {"name": "Gratitude", "score": 0.022960733622312546}, {"name": "Guilt", "score": 0.007196982856839895}, {"name": "Horror", "score": 0.00011552555224625394}, {"name": "Interest", "score": 0.014583174139261246}, {"name": "Joy", "score": 0.00758309056982398}, {"name": "Love", "score": 0.0006768491584807634}, {"name": "Nostalgia", "score": 0.0011878255754709244}, {"name": "Pain", "score": 0.004953945055603981}, {"name": "Pride", "score": 0.004345436114817858}, {"name": "Realization", "score": 0.06731613725423813}, {"name": "Relief", "score": 0.07126811891794205}, {"name": "Romance", "score": 0.00024932087399065495}, {"name": "Sadness", "score": 0.009710087440907955}, {"name": "Sarcasm", "score": 0.02084365114569664}, {"name": "Satisfaction", "score": 0.08344648033380508}, {"name": "Shame", "score": 0.006576063577085733}, {"name": "Surprise (negative)", "score": 0.003977473825216293}, {"name": "Surprise (positive)", "score": 0.003907629754394293}, {"name": "Sympathy", "score": 0.003596843685954809}, {"name": "Tiredness", "score": 0.3231358230113983}, {"name": "Triumph", "score": 0.008732128888368607}], "sentiment": null, "toxicity": null}, {"text": "for", "position": {"begin": 33, "end": 36}, "time": null, "confidence": null, "speaker_confidence": null, "emotions": [{"name": "Admiration", "score": 0.001104738563299179}, {"name": "Adoration", "score": 0.0010656352387741208}, {"name": "Aesthetic Appreciation", "score": 0.003880718257278204}, {"name": "Amusement", "score": 0.018574794754385948}, {"name": "Anger", "score": 0.006416361778974533}, {"name": "Annoyance", "score": 0.2088104486465454}, {"name": "Anxiety", "score": 0.015940671786665916}, {"name": "Awe", "score": 0.0005263694911263883}, {"name": "Awkwardness", "score": 0.09257322549819946}, {"name": "Boredom", "score": 0.30933159589767456}, {"name": "Calmness", "score": 0.42489609122276306}, {"name": "Concentration", "score": 0.025856923311948776}, {"name": "Confusion", "score": 0.024034639820456505}, {"name": "Contemplation", "score": 0.046809908002614975}, {"name": "Contempt", "score": 0.06857159733772278}, {"name": "Contentment", "score": 0.1422223299741745}, {"name": "Craving", "score": 0.005031220614910126}, {"name": "Desire", "score": 0.000955625728238374}, {"name": "Determination", "score": 0.02850520610809326}, {"name": "Disappointment", "score": 0.023154905065894127}, {"name": "Disapproval", "score": 0.02932097390294075}, {"name": "Disgust", "score": 0.004637607838958502}, {"name": "Distress", "score": 0.011248697526752949}, {"name": "Doubt", "score": 0.01927519217133522}, {"name": "Ecstasy", "score": 0.0007188187446445227}, {"name": "Embarrassment", "score": 0.006338654551655054}, {"name": "Empathic Pain", "score": 0.0036224329378455877}, {"name": "Enthusiasm", "score": 0.028997298330068588}, {"name": "Entrancement", "score": 0.002274405211210251}, {"name": "Envy", "score": 0.0007982160313986242}, {"name": "Excitement", "score": 0.007568072993308306}, {"name": "Fear", "score": 0.001427731942385435}, {"name": "Gratitude", "score": 0.03371969982981682}, {"name": "Guilt", "score": 0.00521591491997242}, {"name": "Horror", "score": 0.00013577270146925002}, {"name": "Interest", "score": 0.035069696605205536}, {"name": "Joy", "score": 0.008424999192357063}, {"name": "Love", "score": 0.0019913690630346537}, {"name": "Nostalgia", "score": 0.0011411155574023724}, {"name": "Pain", "score": 0.003163737477734685}, {"name": "Pride", "score": 0.005477208644151688}, {"name": "Realization", "score": 0.030259575694799423}, {"name": "Relief", "score": 0.032171882688999176}, {"name": "Romance", "score": 0.00070796167710796}, {"name": "Sadness", "score": 0.005489415023475885}, {"name": "Sarcasm", "score": 0.08693201839923859}, {"name": "Satisfaction", "score": 0.06851278990507126}, {"name": "Shame", "score": 0.00464321905747056}, {"name": "Surprise (negative)", "score": 0.0039022723212838173}, {"name": "Surprise (positive)", "score": 0.0036351236049085855}, {"name": "Sympathy", "score": 0.005103935021907091}, {"name": "Tiredness", "score": 0.1871146708726883}, {"name": "Triumph", "score": 0.0062845745123922825}], "sentiment": null, "toxicity": null}, {"text": "a", "position": {"begin": 37, "end": 38}, "time": null, "confidence": null, "speaker_confidence": null, "emotions": [{"name": "Admiration", "score": 0.000819369510281831}, {"name": "Adoration", "score": 0.0007230931660160422}, {"name": "Aesthetic Appreciation", "score": 0.0034701821859925985}, {"name": "Amusement", "score": 0.013467887416481972}, {"name": "Anger", "score": 0.003902692813426256}, {"name": "Annoyance", "score": 0.1658148616552353}, {"name": "Anxiety", "score": 0.01731964573264122}, {"name": "Awe", "score": 0.00045251473784446716}, {"name": "Awkwardness", "score": 0.09082350879907608}, {"name": "Boredom", "score": 0.4116764962673187}, {"name": "Calmness", "score": 0.44727393984794617}, {"name": "Concentration", "score": 0.022224636748433113}, {"name": "Confusion", "score": 0.022304560989141464}, {"name": "Contemplation", "score": 0.055366400629282}, {"name": "Contempt", "score": 0.054000239819288254}, {"name": "Contentment", "score": 0.15823572874069214}, {"name": "Craving", "score": 0.0044516632333397865}, {"name": "Desire", "score": 0.0006568807293660939}, {"name": "Determination", "score": 0.01799527183175087}, {"name": "Disappointment", "score": 0.028838075697422028}, {"name": "Disapproval", "score": 0.024036869406700134}, {"name": "Disgust", "score": 0.003810170339420438}, {"name": "Distress", "score": 0.011482249945402145}, {"name": "Doubt", "score": 0.021193381398916245}, {"name": "Ecstasy", "score": 0.000643552397377789}, {"name": "Embarrassment", "score": 0.007281915750354528}, {"name": "Empathic Pain", "score": 0.0036483765579760075}, {"name": "Enthusiasm", "score": 0.018462657928466797}, {"name": "Entrancement", "score": 0.0021702852100133896}, {"name": "Envy", "score": 0.0007137373322620988}, {"name": "Excitement", "score": 0.005096521694213152}, {"name": "Fear", "score": 0.0012528275838121772}, {"name": "Gratitude", "score": 0.02450621873140335}, {"name": "Guilt", "score": 0.00680916290730238}, {"name": "Horror", "score": 0.00010547370038693771}, {"name": "Interest", "score": 0.025225400924682617}, {"name": "Joy", "score": 0.006878595799207687}, {"name": "Love", "score": 0.001234908471815288}, {"name": "Nostalgia", "score": 0.0011363038793206215}, {"name": "Pain", "score": 0.0035066097043454647}, {"name": "Pride", "score": 0.0036272502038627863}, {"name": "Realization", "score": 0.04404501989483833}, {"name": "Relief", "score": 0.04008275270462036}, {"name": "Romance", "score": 0.0005008272710256279}, {"name": "Sadness", "score": 0.007537032477557659}, {"name": "Sarcasm", "score": 0.0439281091094017}, {"name": "Satisfaction", "score": 0.06653552502393723}, {"name": "Shame", "score": 0.0060144574381411076}, {"name": "Surprise (negative)", "score": 0.0036479707341641188}, {"name": "Surprise (positive)", "score": 0.00321556581184268}, {"name": "Sympathy", "score": 0.004959010519087315}, {"name": "Tiredness", "score": 0.2362116426229477}, {"name": "Triumph", "score": 0.0048443288542330265}], "sentiment": null, "toxicity": null}, {"text": "conference.", "position": {"begin": 39, "end": 50}, "time": null, "confidence": null, "speaker_confidence": null, "emotions": [{"name": "Admiration", "score": 0.0014511103508993983}, {"name": "Adoration", "score": 0.0008167855557985604}, {"name": "Aesthetic Appreciation", "score": 0.0057722702622413635}, {"name": "Amusement", "score": 0.008812625892460346}, {"name": "Anger", "score": 0.0029353946447372437}, {"name": "Annoyance", "score": 0.11104530096054077}, {"name": "Anxiety", "score": 0.06271079182624817}, {"name": "Awe", "score": 0.0007763635367155075}, {"name": "Awkwardness", "score": 0.19975224137306213}, {"name": "Boredom", "score": 0.35649871826171875}, {"name": "Calmness", "score": 0.4945145845413208}, {"name": "Concentration", "score": 0.05524211749434471}, {"name": "Confusion", "score": 0.01613551564514637}, {"name": "Contemplation", "score": 0.09953121840953827}, {"name": "Contempt", "score": 0.05147486925125122}, {"name": "Contentment", "score": 0.12554730474948883}, {"name": "Craving", "score": 0.0018356731161475182}, {"name": "Desire", "score": 0.0005273986607789993}, {"name": "Determination", "score": 0.04965877905488014}, {"name": "Disappointment", "score": 0.032140135765075684}, {"name": "Disapproval", "score": 0.031693849712610245}, {"name": "Disgust", "score": 0.003927133046090603}, {"name": "Distress", "score": 0.022330492734909058}, {"name": "Doubt", "score": 0.049738284200429916}, {"name": "Ecstasy", "score": 0.0003726716386154294}, {"name": "Embarrassment", "score": 0.02254645712673664}, {"name": "Empathic Pain", "score": 0.006362859159708023}, {"name": "Enthusiasm", "score": 0.02196057327091694}, {"name": "Entrancement", "score": 0.0036210473626852036}, {"name": "Envy", "score": 0.0011978826951235533}, {"name": "Excitement", "score": 0.005381028167903423}, {"name": "Fear", "score": 0.006760598160326481}, {"name": "Gratitude", "score": 0.010909637436270714}, {"name": "Guilt", "score": 0.011730136349797249}, {"name": "Horror", "score": 0.0002525831514503807}, {"name": "Interest", "score": 0.03776734694838524}, {"name": "Joy", "score": 0.003356114262714982}, {"name": "Love", "score": 0.0008453070186078548}, {"name": "Nostalgia", "score": 0.0010504956590011716}, {"name": "Pain", "score": 0.005472807213664055}, {"name": "Pride", "score": 0.01588146574795246}, {"name": "Realization", "score": 0.0678320899605751}, {"name": "Relief", "score": 0.01763092912733555}, {"name": "Romance", "score": 0.00043984557851217687}, {"name": "Sadness", "score": 0.014523336663842201}, {"name": "Sarcasm", "score": 0.02823144569993019}, {"name": "Satisfaction", "score": 0.050014056265354156}, {"name": "Shame", "score": 0.019857125356793404}, {"name": "Surprise (negative)", "score": 0.004589346703141928}, {"name": "Surprise (positive)", "score": 0.0023382771760225296}, {"name": "Sympathy", "score": 0.006927956826984882}, {"name": "Tiredness", "score": 0.13463573157787323}, {"name": "Triumph", "score": 0.0067076366394758224}], "sentiment": null, "toxicity": null}, {"text": "Umm,", "position": {"begin": 51, "end": 55}, "time": null, "confidence": null, "speaker_confidence": null, "emotions": [{"name": "Admiration", "score": 0.0011675836285576224}, {"name": "Adoration", "score": 0.0006286550196819007}, {"name": "Aesthetic Appreciation", "score": 0.006370358634740114}, {"name": "Amusement", "score": 0.00995195284485817}, {"name": "Anger", "score": 0.0025852599646896124}, {"name": "Annoyance", "score": 0.11601854115724564}, {"name": "Anxiety", "score": 0.18570291996002197}, {"name": "Awe", "score": 0.0008736858144402504}, {"name": "Awkwardness", "score": 0.5950336456298828}, {"name": "Boredom", "score": 0.353360116481781}, {"name": "Calmness", "score": 0.07748479396104813}, {"name": "Concentration", "score": 0.03753868490457535}, {"name": "Confusion", "score": 0.12542040646076202}, {"name": "Contemplation", "score": 0.09614107757806778}, {"name": "Contempt", "score": 0.03961779922246933}, {"name": "Contentment", "score": 0.012925050221383572}, {"name": "Craving", "score": 0.0010726955952122808}, {"name": "Desire", "score": 0.0011679284507408738}, {"name": "Determination", "score": 0.010520239360630512}, {"name": "Disappointment", "score": 0.04004606977105141}, {"name": "Disapproval", "score": 0.05958665534853935}, {"name": "Disgust", "score": 0.0071508619002997875}, {"name": "Distress", "score": 0.043976761400699615}, {"name": "Doubt", "score": 0.24800024926662445}, {"name": "Ecstasy", "score": 0.0002518117253202945}, {"name": "Embarrassment", "score": 0.08989710360765457}, {"name": "Empathic Pain", "score": 0.0038971388712525368}, {"name": "Enthusiasm", "score": 0.008132766000926495}, {"name": "Entrancement", "score": 0.0054757678881287575}, {"name": "Envy", "score": 0.001590081723406911}, {"name": "Excitement", "score": 0.0035673396196216345}, {"name": "Fear", "score": 0.02520773373544216}, {"name": "Gratitude", "score": 0.0018968572840094566}, {"name": "Guilt", "score": 0.008264540694653988}, {"name": "Horror", "score": 0.0008611282100901008}, {"name": "Interest", "score": 0.0216315109282732}, {"name": "Joy", "score": 0.0014168755151331425}, {"name": "Love", "score": 0.00044367529335431755}, {"name": "Nostalgia", "score": 0.001473646960221231}, {"name": "Pain", "score": 0.004726290702819824}, {"name": "Pride", "score": 0.0029974067583680153}, {"name": "Realization", "score": 0.0586123950779438}, {"name": "Relief", "score": 0.0034976843744516373}, {"name": "Romance", "score": 0.0008105914457701147}, {"name": "Sadness", "score": 0.01200814452022314}, {"name": "Sarcasm", "score": 0.018788177520036697}, {"name": "Satisfaction", "score": 0.0053957742638885975}, {"name": "Shame", "score": 0.03542846441268921}, {"name": "Surprise (negative)", "score": 0.011063655838370323}, {"name": "Surprise (positive)", "score": 0.002614707453176379}, {"name": "Sympathy", "score": 0.0031005428172647953}, {"name": "Tiredness", "score": 0.06953208148479462}, {"name": "Triumph", "score": 0.00125977024435997}], "sentiment": null, "toxicity": null}]}]}}}], "errors": []}}]