[{"source": {"type": "file", "filename": "640_00-00-09.301_00-00-10.386_Joanna_neutral_neutral.txt", "content_type": "text/plain", "md5sum": "49a746cf429cd9e92defe0b708fdec57"}, "results": {"predictions": [{"file": "640_00-00-09.301_00-00-10.386_Joanna_neutral_neutral.txt", "file_type": "text", "models": {"language": {"metadata": null, "grouped_predictions": [{"id": "unknown", "predictions": [{"text": "Filing", "position": {"begin": 0, "end": 6}, "time": null, "confidence": null, "speaker_confidence": null, "emotions": [{"name": "Admiration", "score": 0.0021268774289637804}, {"name": "Adoration", "score": 0.0012185925152152777}, {"name": "Aesthetic Appreciation", "score": 0.012682509608566761}, {"name": "Amusement", "score": 0.01766834408044815}, {"name": "Anger", "score": 0.002099310979247093}, {"name": "Annoyance", "score": 0.028191300109028816}, {"name": "Anxiety", "score": 0.00814390741288662}, {"name": "Awe", "score": 0.001979142427444458}, {"name": "Awkwardness", "score": 0.027988534420728683}, {"name": "Boredom", "score": 0.2069920152425766}, {"name": "Calmness", "score": 0.13320650160312653}, {"name": "Concentration", "score": 0.1388084590435028}, {"name": "Confusion", "score": 0.14815929532051086}, {"name": "Contemplation", "score": 0.0687832310795784}, {"name": "Contempt", "score": 0.01694260537624359}, {"name": "Contentment", "score": 0.06999944150447845}, {"name": "Craving", "score": 0.003966513555496931}, {"name": "Desire", "score": 0.0011150448117405176}, {"name": "Determination", "score": 0.026632461696863174}, {"name": "Disappointment", "score": 0.00891876220703125}, {"name": "Disapproval", "score": 0.003548539010807872}, {"name": "Disgust", "score": 0.0012469710782170296}, {"name": "Distress", "score": 0.005827878601849079}, {"name": "Doubt", "score": 0.015465994365513325}, {"name": "Ecstasy", "score": 0.004927685018628836}, {"name": "Embarrassment", "score": 0.004117986187338829}, {"name": "Empathic Pain", "score": 0.001011432963423431}, {"name": "Enthusiasm", "score": 0.01827542670071125}, {"name": "Entrancement", "score": 0.010933510027825832}, {"name": "Envy", "score": 0.0007968312711454928}, {"name": "Excitement", "score": 0.010742568410933018}, {"name": "Fear", "score": 0.0014390830183401704}, {"name": "Gratitude", "score": 0.004152939189225435}, {"name": "Guilt", "score": 0.0017766227247193456}, {"name": "Horror", "score": 0.0004605723370332271}, {"name": "Interest", "score": 0.024904143065214157}, {"name": "Joy", "score": 0.014227387495338917}, {"name": "Love", "score": 0.001005142810754478}, {"name": "Nostalgia", "score": 0.02984747290611267}, {"name": "Pain", "score": 0.0033769661094993353}, {"name": "Pride", "score": 0.011020832695066929}, {"name": "Realization", "score": 0.04747147858142853}, {"name": "Relief", "score": 0.01950949802994728}, {"name": "Romance", "score": 0.0007835854194127023}, {"name": "Sadness", "score": 0.003524089464917779}, {"name": "Sarcasm", "score": 0.004410635679960251}, {"name": "Satisfaction", "score": 0.05986110866069794}, {"name": "Shame", "score": 0.004508959595113993}, {"name": "Surprise (negative)", "score": 0.0067553287371993065}, {"name": "Surprise (positive)", "score": 0.00819745659828186}, {"name": "Sympathy", "score": 0.0010355317499488592}, {"name": "Tiredness", "score": 0.04372038692235947}, {"name": "Triumph", "score": 0.03829581290483475}], "sentiment": null, "toxicity": null}, {"text": "system?", "position": {"begin": 7, "end": 14}, "time": null, "confidence": null, "speaker_confidence": null, "emotions": [{"name": "Admiration", "score": 0.00452967407181859}, {"name": "Adoration", "score": 0.001090542646124959}, {"name": "Aesthetic Appreciation", "score": 0.0243987999856472}, {"name": "Amusement", "score": 0.03588271141052246}, {"name": "Anger", "score": 0.0007421792834065855}, {"name": "Annoyance", "score": 0.015227711759507656}, {"name": "Anxiety", "score": 0.008260326460003853}, {"name": "Awe", "score": 0.0040834816172719}, {"name": "Awkwardness", "score": 0.035060375928878784}, {"name": "Boredom", "score": 0.03472605347633362}, {"name": "Calmness", "score": 0.03425641730427742}, {"name": "Concentration", "score": 0.16261103749275208}, {"name": "Confusion", "score": 0.6182826161384583}, {"name": "Contemplation", "score": 0.138483926653862}, {"name": "Contempt", "score": 0.008901338092982769}, {"name": "Contentment", "score": 0.013314727693796158}, {"name": "Craving", "score": 0.002466658130288124}, {"name": "Desire", "score": 0.0007161396206356585}, {"name": "Determination", "score": 0.011348916217684746}, {"name": "Disappointment", "score": 0.005623723845928907}, {"name": "Disapproval", "score": 0.00445343554019928}, {"name": "Disgust", "score": 0.0014396820915862918}, {"name": "Distress", "score": 0.004152616020292044}, {"name": "Doubt", "score": 0.08055993914604187}, {"name": "Ecstasy", "score": 0.0017138015246018767}, {"name": "Embarrassment", "score": 0.0051808953285217285}, {"name": "Empathic Pain", "score": 0.0007379548042081296}, {"name": "Enthusiasm", "score": 0.024620966985821724}, {"name": "Entrancement", "score": 0.014004039578139782}, {"name": "Envy", "score": 0.0005954919615760446}, {"name": "Excitement", "score": 0.009765388444066048}, {"name": "Fear", "score": 0.002386870328336954}, {"name": "Gratitude", "score": 0.002196485409513116}, {"name": "Guilt", "score": 0.0008986374014057219}, {"name": "Horror", "score": 0.0006609415868297219}, {"name": "Interest", "score": 0.20224601030349731}, {"name": "Joy", "score": 0.006441565230488777}, {"name": "Love", "score": 0.0004060202627442777}, {"name": "Nostalgia", "score": 0.004234655294567347}, {"name": "Pain", "score": 0.0006944076740182936}, {"name": "Pride", "score": 0.003950315527617931}, {"name": "Realization", "score": 0.036233626306056976}, {"name": "Relief", "score": 0.0021575563587248325}, {"name": "Romance", "score": 0.00028666615253314376}, {"name": "Sadness", "score": 0.0005530457128770649}, {"name": "Sarcasm", "score": 0.01004746649414301}, {"name": "Satisfaction", "score": 0.0231013186275959}, {"name": "Shame", "score": 0.0023925064597278833}, {"name": "Surprise (negative)", "score": 0.019104760140180588}, {"name": "Surprise (positive)", "score": 0.029076388105750084}, {"name": "Sympathy", "score": 0.0008088939939625561}, {"name": "Tiredness", "score": 0.004649392329156399}, {"name": "Triumph", "score": 0.006718413904309273}], "sentiment": null, "toxicity": null}]}]}}}], "errors": []}}]