[{"source": {"type": "file", "filename": "784_00-00-11.095_00-00-18.518_Rachel_sadness_negative.mp3", "content_type": "audio/mpeg", "md5sum": "c34460eaef2bbd2f2e447f660168931b"}, "results": {"predictions": [{"file": "784_00-00-11.095_00-00-18.518_Rachel_sadness_negative.mp3", "file_type": "audio", "models": {"prosody": {"metadata": {"confidence": 0.82177734, "detected_language": "en"}, "grouped_predictions": [{"id": "unknown", "predictions": [{"text": "Got that woman sitting out by the pool getting tan. Material", "time": {"begin": 0.28, "end": 3.4199998}, "confidence": 0.908647, "speaker_confidence": null, "emotions": [{"name": "Admiration", "score": 0.03863100707530975}, {"name": "Adoration", "score": 0.013595744967460632}, {"name": "Aesthetic Appreciation", "score": 0.04680435359477997}, {"name": "Amusement", "score": 0.19937384128570557}, {"name": "Anger", "score": 0.19540956616401672}, {"name": "Anxiety", "score": 0.030266130343079567}, {"name": "Awe", "score": 0.01593179628252983}, {"name": "Awkwardness", "score": 0.05587084963917732}, {"name": "Boredom", "score": 0.06693384051322937}, {"name": "Calmness", "score": 0.045310162007808685}, {"name": "Concentration", "score": 0.04988844692707062}, {"name": "Confusion", "score": 0.03780679404735565}, {"name": "Contemplation", "score": 0.031240995973348618}, {"name": "Contempt", "score": 0.2666001617908478}, {"name": "Contentment", "score": 0.013773307204246521}, {"name": "Craving", "score": 0.030431007966399193}, {"name": "Desire", "score": 0.016109827905893326}, {"name": "Determination", "score": 0.021939875558018684}, {"name": "Disappointment", "score": 0.17018863558769226}, {"name": "Disgust", "score": 0.1803361475467682}, {"name": "Distress", "score": 0.12254857271909714}, {"name": "Doubt", "score": 0.010527045466005802}, {"name": "Ecstasy", "score": 0.005848671775311232}, {"name": "Embarrassment", "score": 0.04575364291667938}, {"name": "Empathic Pain", "score": 0.021391429007053375}, {"name": "Entrancement", "score": 0.01201392337679863}, {"name": "Envy", "score": 0.15958794951438904}, {"name": "Excitement", "score": 0.02297966368496418}, {"name": "Fear", "score": 0.0490943118929863}, {"name": "Guilt", "score": 0.020757324993610382}, {"name": "Horror", "score": 0.06953631341457367}, {"name": "Interest", "score": 0.02801479771733284}, {"name": "Joy", "score": 0.009537351317703724}, {"name": "Love", "score": 0.008078282698988914}, {"name": "Nostalgia", "score": 0.08186040818691254}, {"name": "Pain", "score": 0.03486202284693718}, {"name": "Pride", "score": 0.016516458243131638}, {"name": "Realization", "score": 0.012072705663740635}, {"name": "Relief", "score": 0.006649751216173172}, {"name": "Romance", "score": 0.015342499129474163}, {"name": "Sadness", "score": 0.05499555543065071}, {"name": "Satisfaction", "score": 0.014476911164820194}, {"name": "Shame", "score": 0.016003739088773727}, {"name": "Surprise (negative)", "score": 0.08029916882514954}, {"name": "Surprise (positive)", "score": 0.011683083139359951}, {"name": "Sympathy", "score": 0.020545706152915955}, {"name": "Tiredness", "score": 0.019522948190569878}, {"name": "Triumph", "score": 0.007166916038841009}]}, {"text": "she's a leather wrinkled pushing she just.", "time": {"begin": 4.2799997, "end": 6.2}, "confidence": 0.5006452, "speaker_confidence": null, "emotions": [{"name": "Admiration", "score": 0.010065259411931038}, {"name": "Adoration", "score": 0.0048031313344836235}, {"name": "Aesthetic Appreciation", "score": 0.009243816137313843}, {"name": "Amusement", "score": 0.02873106487095356}, {"name": "Anger", "score": 0.6962084174156189}, {"name": "Anxiety", "score": 0.08628243952989578}, {"name": "Awe", "score": 0.01627177745103836}, {"name": "Awkwardness", "score": 0.02439221367239952}, {"name": "Boredom", "score": 0.0020788167603313923}, {"name": "Calmness", "score": 0.0007550205336883664}, {"name": "Concentration", "score": 0.004066145047545433}, {"name": "Confusion", "score": 0.03486137092113495}, {"name": "Contemplation", "score": 0.0021888643968850374}, {"name": "Contempt", "score": 0.2245982438325882}, {"name": "Contentment", "score": 0.001394652877934277}, {"name": "Craving", "score": 0.004285898990929127}, {"name": "Desire", "score": 0.004298122599720955}, {"name": "Determination", "score": 0.009405743330717087}, {"name": "Disappointment", "score": 0.07447636127471924}, {"name": "Disgust", "score": 0.37912407517433167}, {"name": "Distress", "score": 0.23017406463623047}, {"name": "Doubt", "score": 0.007904326543211937}, {"name": "Ecstasy", "score": 0.016371946781873703}, {"name": "Embarrassment", "score": 0.019800972193479538}, {"name": "Empathic Pain", "score": 0.011083151213824749}, {"name": "Entrancement", "score": 0.0034202905371785164}, {"name": "Envy", "score": 0.013925514183938503}, {"name": "Excitement", "score": 0.042520277202129364}, {"name": "Fear", "score": 0.08225192129611969}, {"name": "Guilt", "score": 0.010272407904267311}, {"name": "Horror", "score": 0.14829668402671814}, {"name": "Interest", "score": 0.007675123400986195}, {"name": "Joy", "score": 0.004423698876053095}, {"name": "Love", "score": 0.0016321241855621338}, {"name": "Nostalgia", "score": 0.003759654238820076}, {"name": "Pain", "score": 0.029905742034316063}, {"name": "Pride", "score": 0.0032047720160335302}, {"name": "Realization", "score": 0.017010116949677467}, {"name": "Relief", "score": 0.00150535989087075}, {"name": "Romance", "score": 0.0031683151610195637}, {"name": "Sadness", "score": 0.010251269675791264}, {"name": "Satisfaction", "score": 0.004257758613675833}, {"name": "Shame", "score": 0.01746712252497673}, {"name": "Surprise (negative)", "score": 0.2669193744659424}, {"name": "Surprise (positive)", "score": 0.012016646564006805}, {"name": "Sympathy", "score": 0.0029899203218519688}, {"name": "Tiredness", "score": 0.011507945135235786}, {"name": "Triumph", "score": 0.004963119048625231}]}]}]}}}], "errors": []}}]