[{"source": {"type": "file", "filename": "828_00-00-00.000_00-00-02.335_Woman_anger_negative.txt", "content_type": "text/plain", "md5sum": "041c2a31088740a7c7d354cc02e5d6cf"}, "results": {"predictions": [{"file": "828_00-00-00.000_00-00-02.335_Woman_anger_negative.txt", "file_type": "text", "models": {"language": {"metadata": null, "grouped_predictions": [{"id": "unknown", "predictions": [{"text": "Comin'", "position": {"begin": 0, "end": 6}, "time": null, "confidence": null, "speaker_confidence": null, "emotions": [{"name": "Admiration", "score": 0.0034262717235833406}, {"name": "Adoration", "score": 0.005109179764986038}, {"name": "Aesthetic Appreciation", "score": 0.005113485734909773}, {"name": "Amusement", "score": 0.02028999850153923}, {"name": "Anger", "score": 0.00895630195736885}, {"name": "Annoyance", "score": 0.03346676751971245}, {"name": "Anxiety", "score": 0.02359181083738804}, {"name": "Awe", "score": 0.003041269024834037}, {"name": "Awkwardness", "score": 0.014984073117375374}, {"name": "Boredom", "score": 0.029916804283857346}, {"name": "Calmness", "score": 0.2689567804336548}, {"name": "Concentration", "score": 0.08160552382469177}, {"name": "Confusion", "score": 0.0072084288112819195}, {"name": "Contemplation", "score": 0.02021186053752899}, {"name": "Contempt", "score": 0.02660902962088585}, {"name": "Contentment", "score": 0.0789678543806076}, {"name": "Craving", "score": 0.014586253091692924}, {"name": "Desire", "score": 0.010536245070397854}, {"name": "Determination", "score": 0.2779536545276642}, {"name": "Disappointment", "score": 0.0030446818564087152}, {"name": "Disapproval", "score": 0.008165826089680195}, {"name": "Disgust", "score": 0.002046135952696204}, {"name": "Distress", "score": 0.009793959558010101}, {"name": "Doubt", "score": 0.005299997981637716}, {"name": "Ecstasy", "score": 0.01657542586326599}, {"name": "Embarrassment", "score": 0.0005971313221380115}, {"name": "Empathic Pain", "score": 0.003445618785917759}, {"name": "Enthusiasm", "score": 0.35427233576774597}, {"name": "Entrancement", "score": 0.007903387770056725}, {"name": "Envy", "score": 0.0008957934333011508}, {"name": "Excitement", "score": 0.3182229697704315}, {"name": "Fear", "score": 0.008571254089474678}, {"name": "Gratitude", "score": 0.008402140811085701}, {"name": "Guilt", "score": 0.0007008944521658123}, {"name": "Horror", "score": 0.0008593586389906704}, {"name": "Interest", "score": 0.14295609295368195}, {"name": "Joy", "score": 0.05652805417776108}, {"name": "Love", "score": 0.010046458803117275}, {"name": "Nostalgia", "score": 0.001158726285211742}, {"name": "Pain", "score": 0.0017953173955902457}, {"name": "Pride", "score": 0.012866652570664883}, {"name": "Realization", "score": 0.015178302302956581}, {"name": "Relief", "score": 0.024222707375884056}, {"name": "Romance", "score": 0.006665039341896772}, {"name": "Sadness", "score": 0.0012887818738818169}, {"name": "Sarcasm", "score": 0.013889964669942856}, {"name": "Satisfaction", "score": 0.08484719693660736}, {"name": "Shame", "score": 0.000823132402729243}, {"name": "Surprise (negative)", "score": 0.005796976387500763}, {"name": "Surprise (positive)", "score": 0.017280355095863342}, {"name": "Sympathy", "score": 0.004697974771261215}, {"name": "Tiredness", "score": 0.009271012619137764}, {"name": "Triumph", "score": 0.04597703740000725}], "sentiment": null, "toxicity": null}, {"text": "through.", "position": {"begin": 7, "end": 15}, "time": null, "confidence": null, "speaker_confidence": null, "emotions": [{"name": "Admiration", "score": 0.003861663630232215}, {"name": "Adoration", "score": 0.0021447986364364624}, {"name": "Aesthetic Appreciation", "score": 0.003518893150612712}, {"name": "Amusement", "score": 0.01966782659292221}, {"name": "Anger", "score": 0.007875374518334866}, {"name": "Annoyance", "score": 0.0306490957736969}, {"name": "Anxiety", "score": 0.027595411986112595}, {"name": "Awe", "score": 0.0036712989676743746}, {"name": "Awkwardness", "score": 0.007194770034402609}, {"name": "Boredom", "score": 0.027931252494454384}, {"name": "Calmness", "score": 0.09900540858507156}, {"name": "Concentration", "score": 0.12790802121162415}, {"name": "Confusion", "score": 0.009946845471858978}, {"name": "Contemplation", "score": 0.027072668075561523}, {"name": "Contempt", "score": 0.016088740900158882}, {"name": "Contentment", "score": 0.07554007321596146}, {"name": "Craving", "score": 0.0038341146428138018}, {"name": "Desire", "score": 0.0013150080339983106}, {"name": "Determination", "score": 0.59089195728302}, {"name": "Disappointment", "score": 0.009613524191081524}, {"name": "Disapproval", "score": 0.0038318189326673746}, {"name": "Disgust", "score": 0.0009819298284128308}, {"name": "Distress", "score": 0.025483878329396248}, {"name": "Doubt", "score": 0.007253430318087339}, {"name": "Ecstasy", "score": 0.01276744157075882}, {"name": "Embarrassment", "score": 0.0015401029959321022}, {"name": "Empathic Pain", "score": 0.0035462945234030485}, {"name": "Enthusiasm", "score": 0.16087324917316437}, {"name": "Entrancement", "score": 0.00736268563196063}, {"name": "Envy", "score": 0.0005196402780711651}, {"name": "Excitement", "score": 0.11364113539457321}, {"name": "Fear", "score": 0.01389176957309246}, {"name": "Gratitude", "score": 0.007728685159236193}, {"name": "Guilt", "score": 0.0008282400667667389}, {"name": "Horror", "score": 0.0011269223177805543}, {"name": "Interest", "score": 0.018958982080221176}, {"name": "Joy", "score": 0.032656967639923096}, {"name": "Love", "score": 0.004076946992427111}, {"name": "Nostalgia", "score": 0.005581303965300322}, {"name": "Pain", "score": 0.017108015716075897}, {"name": "Pride", "score": 0.07871019095182419}, {"name": "Realization", "score": 0.031309448182582855}, {"name": "Relief", "score": 0.05925707891583443}, {"name": "Romance", "score": 0.0014311299892142415}, {"name": "Sadness", "score": 0.01035358291119337}, {"name": "Sarcasm", "score": 0.018616480752825737}, {"name": "Satisfaction", "score": 0.1003507748246193}, {"name": "Shame", "score": 0.0019410529639571905}, {"name": "Surprise (negative)", "score": 0.006938525941222906}, {"name": "Surprise (positive)", "score": 0.01178580429404974}, {"name": "Sympathy", "score": 0.002526580123230815}, {"name": "Tiredness", "score": 0.031412217766046524}, {"name": "Triumph", "score": 0.3361186385154724}], "sentiment": null, "toxicity": null}, {"text": "Move,", "position": {"begin": 16, "end": 21}, "time": null, "confidence": null, "speaker_confidence": null, "emotions": [{"name": "Admiration", "score": 0.0021048826165497303}, {"name": "Adoration", "score": 0.0014736797893419862}, {"name": "Aesthetic Appreciation", "score": 0.004304342903196812}, {"name": "Amusement", "score": 0.013104810379445553}, {"name": "Anger", "score": 0.02440444752573967}, {"name": "Annoyance", "score": 0.10703620314598083}, {"name": "Anxiety", "score": 0.017949316650629044}, {"name": "Awe", "score": 0.0011841156519949436}, {"name": "Awkwardness", "score": 0.01614239253103733}, {"name": "Boredom", "score": 0.06398951262235641}, {"name": "Calmness", "score": 0.1009218618273735}, {"name": "Concentration", "score": 0.15172678232192993}, {"name": "Confusion", "score": 0.010424479842185974}, {"name": "Contemplation", "score": 0.012048404663801193}, {"name": "Contempt", "score": 0.032016005367040634}, {"name": "Contentment", "score": 0.044198304414749146}, {"name": "Craving", "score": 0.005796308163553476}, {"name": "Desire", "score": 0.005044371355324984}, {"name": "Determination", "score": 0.6316549777984619}, {"name": "Disappointment", "score": 0.012976560741662979}, {"name": "Disapproval", "score": 0.01542783621698618}, {"name": "Disgust", "score": 0.003405580762773752}, {"name": "Distress", "score": 0.02534891851246357}, {"name": "Doubt", "score": 0.005899134092032909}, {"name": "Ecstasy", "score": 0.005527448374778032}, {"name": "Embarrassment", "score": 0.0020562419667840004}, {"name": "Empathic Pain", "score": 0.002893587574362755}, {"name": "Enthusiasm", "score": 0.13674163818359375}, {"name": "Entrancement", "score": 0.004146035760641098}, {"name": "Envy", "score": 0.0006633694283664227}, {"name": "Excitement", "score": 0.06186836585402489}, {"name": "Fear", "score": 0.007755944970995188}, {"name": "Gratitude", "score": 0.004162192344665527}, {"name": "Guilt", "score": 0.0009207872790284455}, {"name": "Horror", "score": 0.0010680595878511667}, {"name": "Interest", "score": 0.025625305250287056}, {"name": "Joy", "score": 0.011614295653998852}, {"name": "Love", "score": 0.002922303741797805}, {"name": "Nostalgia", "score": 0.0025824897456914186}, {"name": "Pain", "score": 0.010954035446047783}, {"name": "Pride", "score": 0.034523721784353256}, {"name": "Realization", "score": 0.01491539366543293}, {"name": "Relief", "score": 0.02391795814037323}, {"name": "Romance", "score": 0.0018229375127702951}, {"name": "Sadness", "score": 0.0057462952099740505}, {"name": "Sarcasm", "score": 0.017324481159448624}, {"name": "Satisfaction", "score": 0.05889030545949936}, {"name": "Shame", "score": 0.002176153939217329}, {"name": "Surprise (negative)", "score": 0.008454175665974617}, {"name": "Surprise (positive)", "score": 0.006327909883111715}, {"name": "Sympathy", "score": 0.002505271229892969}, {"name": "Tiredness", "score": 0.04508539289236069}, {"name": "Triumph", "score": 0.13893640041351318}], "sentiment": null, "toxicity": null}, {"text": "move.", "position": {"begin": 22, "end": 27}, "time": null, "confidence": null, "speaker_confidence": null, "emotions": [{"name": "Admiration", "score": 0.001981722889468074}, {"name": "Adoration", "score": 0.0011124610900878906}, {"name": "Aesthetic Appreciation", "score": 0.003714451100677252}, {"name": "Amusement", "score": 0.01265629194676876}, {"name": "Anger", "score": 0.026678601279854774}, {"name": "Annoyance", "score": 0.09606391936540604}, {"name": "Anxiety", "score": 0.029322108253836632}, {"name": "Awe", "score": 0.0014108017785474658}, {"name": "Awkwardness", "score": 0.015504664741456509}, {"name": "Boredom", "score": 0.04617321118712425}, {"name": "Calmness", "score": 0.05890693515539169}, {"name": "Concentration", "score": 0.1840345710515976}, {"name": "Confusion", "score": 0.01512414962053299}, {"name": "Contemplation", "score": 0.012235156260430813}, {"name": "Contempt", "score": 0.025465061888098717}, {"name": "Contentment", "score": 0.027661163359880447}, {"name": "Craving", "score": 0.005734442267566919}, {"name": "Desire", "score": 0.004832246340811253}, {"name": "Determination", "score": 0.6497092247009277}, {"name": "Disappointment", "score": 0.012157302349805832}, {"name": "Disapproval", "score": 0.013901681639254093}, {"name": "Disgust", "score": 0.003581245429813862}, {"name": "Distress", "score": 0.04098059982061386}, {"name": "Doubt", "score": 0.00800158642232418}, {"name": "Ecstasy", "score": 0.006509306374937296}, {"name": "Embarrassment", "score": 0.002334743971005082}, {"name": "Empathic Pain", "score": 0.0027452632784843445}, {"name": "Enthusiasm", "score": 0.12686090171337128}, {"name": "Entrancement", "score": 0.004723942372947931}, {"name": "Envy", "score": 0.0005625109770335257}, {"name": "Excitement", "score": 0.06761787831783295}, {"name": "Fear", "score": 0.017100807279348373}, {"name": "Gratitude", "score": 0.0028395941480994225}, {"name": "Guilt", "score": 0.0008339169435203075}, {"name": "Horror", "score": 0.00214941892772913}, {"name": "Interest", "score": 0.02504792809486389}, {"name": "Joy", "score": 0.008432967588305473}, {"name": "Love", "score": 0.0017241102177649736}, {"name": "Nostalgia", "score": 0.0021221160423010588}, {"name": "Pain", "score": 0.014779102988541126}, {"name": "Pride", "score": 0.029879223555326462}, {"name": "Realization", "score": 0.015560497529804707}, {"name": "Relief", "score": 0.020904170349240303}, {"name": "Romance", "score": 0.001276509603485465}, {"name": "Sadness", "score": 0.005707177799195051}, {"name": "Sarcasm", "score": 0.013786913827061653}, {"name": "Satisfaction", "score": 0.04463746026158333}, {"name": "Shame", "score": 0.0022340307477861643}, {"name": "Surprise (negative)", "score": 0.012413757853209972}, {"name": "Surprise (positive)", "score": 0.007325397804379463}, {"name": "Sympathy", "score": 0.0020537623204290867}, {"name": "Tiredness", "score": 0.03815995529294014}, {"name": "Triumph", "score": 0.1417534351348877}], "sentiment": null, "toxicity": null}]}]}}}], "errors": []}}]